txtstyle/__init__.py
txtstyle/confparser.py
txtstyle/linestyleprocessor.py
txtstyle/palette.py
txtstyle/transformer.py
txtstyle/txts.py
txtstyle/txtsconf.py
txtstyle/version.py
TxtStyle-1.1.2.dist-info/LICENSE.txt
TxtStyle-1.1.2.dist-info/METADATA
TxtStyle-1.1.2.dist-info/WHEEL
TxtStyle-1.1.2.dist-info/entry_points.txt
TxtStyle-1.1.2.dist-info/top_level.txt
TxtStyle-1.1.2.dist-info/RECORD
