Metadata-Version: 2.1
Name: TxtStyle
Version: 1.1.2
Summary: Command-line tool for colorizing output of log files and console programs
Home-page: https://github.com/armandino/TxtStyle
Author: Arman Sharif
Author-email: armandino@gmail.com
License: LICENSE.txt
Project-URL: Bug Reports, https://github.com/armandino/TxtStyle/issues
Project-URL: Source, https://github.com/armandino/TxtStyle
Keywords: color log console text processing
Classifier: Development Status :: 5 - Production/Stable
Classifier: Programming Language :: Python :: 3
Classifier: License :: OSI Approved :: Apache Software License
Classifier: Operating System :: OS Independent
Classifier: Programming Language :: Python
Classifier: Programming Language :: Python :: 3
Classifier: Programming Language :: Python :: 3.7
Classifier: Programming Language :: Python :: 3.8
Classifier: Topic :: Utilities
Requires-Python: >=3.2, <4
License-File: LICENSE.txt
